oscarcch/__init__.py
oscarcch/admin.py
oscarcch/apps.py
oscarcch/calculator.py
oscarcch/exceptions.py
oscarcch/mixins.py
oscarcch/models.py
oscarcch/prices.py
oscarcch/py.typed
oscarcch/settings.py
oscarcch/types.py
oscarcch/locale/es/LC_MESSAGES/django.mo
oscarcch/locale/es/LC_MESSAGES/django.po
oscarcch/migrations/0001_initial.py
oscarcch/migrations/0002_shippingtaxation_shippingtaxationdetail.py
oscarcch/migrations/__init__.py
oscarcch/tests/__init__.py
oscarcch/tests/base.py
oscarcch/tests/test_cch.py
oscarcch/tests/test_cch_nine_digits_zip.py
oscarcch/tests/test_cch_real.py
oscarcch/tests/test_persist_taxation_details.py
oscarcch/tests/test_taxation_details.py
django_oscar_cch-7.5.1.dist-info/METADATA
django_oscar_cch-7.5.1.dist-info/WHEEL
django_oscar_cch-7.5.1.dist-info/licenses/LICENSE
django_oscar_cch-7.5.1.dist-info/RECORD
