Metadata-Version: 2.4
Name: django-oscar-cch
Version: 7.5.1
Summary: Integration between django-oscar and the CCH Sales Tax Office SOAP API.
Project-URL: Homepage, https://gitlab.com/thelabnyc/django-oscar/django-oscar-cch
Project-URL: Repository, https://gitlab.com/thelabnyc/django-oscar/django-oscar-cch
Author-email: thelab <thelabdev@thelab.co>
License: ISC
License-File: LICENSE
Requires-Python: >=3.12
Requires-Dist: django-oscar<4.1,>=4.0
Requires-Dist: django-stubs-ext<6,>=5.1.3
Requires-Dist: django>=4.2
Requires-Dist: zeep<5,>=4.3.1
Provides-Extra: circuitbreaker
Requires-Dist: pybreaker<2,>=1.3.0; extra == 'circuitbreaker'
